okrolearn/__about__.py
okrolearn/__innit__.py
okrolearn/dataloader.py
okrolearn/dataset.py
okrolearn/okrolanalysis.py
okrolearn/okrolearn.py
okrolearn/okroltext.py
okrolearn/okrolvision.py
okrolearn/optimizers.py
okrolearn/tensor.py
okrolearn-2.7.0.dist-info/METADATA
okrolearn-2.7.0.dist-info/WHEEL
okrolearn-2.7.0.dist-info/licenses/LICENSE
okrolearn-2.7.0.dist-info/RECORD
