Metadata-Version: 2.3
Name: okrolearn
Version: 2.7.0
Summary: A machine learning library created by Okerew, which is supposed to be a raw implementation of combining pytorch with scikit-learn
Project-URL: Documentation, https://github.com/Okerew/okrolearn#readme
Project-URL: Issues, https://github.com/Okerew/okrolearn/issues
Project-URL: Source, https://github.com/Okerew/okrolearn
Author-email: Okerew <93822247+Okerew@users.noreply.github.com>
License-Expression: MIT
License-File: LICENSE
Classifier: Development Status :: 4 - Beta
Classifier: Programming Language :: Python
Classifier: Programming Language :: Python :: 3.8
Classifier: Programming Language :: Python :: 3.9
Classifier: Programming Language :: Python :: 3.10
Classifier: Programming Language :: Python :: 3.11
Classifier: Programming Language :: Python :: 3.12
Classifier: Programming Language :: Python :: Implementation :: CPython
Classifier: Programming Language :: Python :: Implementation :: PyPy
Requires-Python: >=3.8
Requires-Dist: cupy
Requires-Dist: matplotlib
Requires-Dist: numpy
Requires-Dist: opencv-python
Requires-Dist: pandas
Requires-Dist: pillow
Requires-Dist: psutil
Requires-Dist: scipy
Requires-Dist: statsmodels
